{
	"configurations" : 
	[
		{
			"directories" : 
			[
				{
					"build" : ".",
					"jsonFile" : "directory-.-Debug-f5ebdc15457944623624.json",
					"minimumCMakeVersion" : 
					{
						"string" : "3.8"
					},
					"projectIndex" : 0,
					"source" : ".",
					"targetIndexes" : 
					[
						0,
						1
					]
				}
			],
			"name" : "Debug",
			"projects" : 
			[
				{
					"directoryIndexes" : 
					[
						0
					],
					"name" : "maze_runner",
					"targetIndexes" : 
					[
						0,
						1
					]
				}
			],
			"targets" : 
			[
				{
					"directoryIndex" : 0,
					"id" : "maze_run::@6890427a1f51a3e7e1df",
					"jsonFile" : "target-maze_run-Debug-c57f9eff3b209aa7b0ef.json",
					"name" : "maze_run",
					"projectIndex" : 0
				},
				{
					"directoryIndex" : 0,
					"id" : "test_gener::@6890427a1f51a3e7e1df",
					"jsonFile" : "target-test_gener-Debug-c524b2a9240498cc36ce.json",
					"name" : "test_gener",
					"projectIndex" : 0
				}
			]
		}
	],
	"kind" : "codemodel",
	"paths" : 
	{
		"build" : "/mnt/c/Users/Maces/Documents/VSB/2L/cpp_advanced/proj/pokus1/build",
		"source" : "/mnt/c/Users/Maces/Documents/VSB/2L/cpp_advanced/proj/pokus1"
	},
	"version" : 
	{
		"major" : 2,
		"minor" : 3
	}
}
